data3_network_variables/__init__.py
data3_network_variables/variables.py
data3_network_variables-0.0.9.dist-info/METADATA
data3_network_variables-0.0.9.dist-info/WHEEL
data3_network_variables-0.0.9.dist-info/top_level.txt
data3_network_variables-0.0.9.dist-info/RECORD
