Metadata-Version: 2.2
Name: data3_network_variables
Version: 0.0.9
Summary: Data3 Network Library for variable access
Author: Data3 Network
Author-email: data3network@gmail.com
Requires-Dist: redis==5.0.8
Requires-Dist: requests==2.32.3
Dynamic: author
Dynamic: author-email
Dynamic: requires-dist
Dynamic: summary
